inventree_cups/__init__.py
inventree_cups/core.py
inventree_cups_plugin-1.1.2.dist-info/licenses/LICENSE
inventree_cups_plugin-1.1.2.dist-info/METADATA
inventree_cups_plugin-1.1.2.dist-info/WHEEL
inventree_cups_plugin-1.1.2.dist-info/entry_points.txt
inventree_cups_plugin-1.1.2.dist-info/top_level.txt
inventree_cups_plugin-1.1.2.dist-info/RECORD
