Metadata-Version: 2.4
Name: inventree-cups-plugin
Version: 1.1.2
Summary: Cups label printer plugin for InvenTree
Author-email: wolflu05 <76838159+wolflu05@users.noreply.github.com>
License-Expression: MIT
Project-URL: Homepage, https://github.com/wolflu05/inventree-cups-plugin
Keywords: inventree,plugin
Classifier: Programming Language :: Python :: 3
Classifier: Operating System :: OS Independent
Classifier: Framework :: InvenTree
Requires-Python: >=3.9
License-File: LICENSE
Requires-Dist: pycups
Dynamic: license-file
